CBOE_downloader/__init__.py
CBOE_downloader/app.py
cboe_downloader2-1.3.dist-info/LICENSE
cboe_downloader2-1.3.dist-info/METADATA
cboe_downloader2-1.3.dist-info/WHEEL
cboe_downloader2-1.3.dist-info/top_level.txt
cboe_downloader2-1.3.dist-info/RECORD
